airflow/__init__.py
airflow/www/static/dataflow-airflow-logo.png
airflow/www/static/logo.png
airflow/www/static/dist/airflowDefaultTheme.f664c2f31c2dd026f579.css
airflow/www/static/dist/chart.46bd6c23eda50252101e.css
airflow/www/static/dist/graph.d7b9049cf1bc674b5c40.css
airflow/www/static/dist/main.8461584ab30f513901c2.css
airflow/www/static/dist/switch.5dc547a0258cf18ca1e2.css
airflow/www/templates/appbuilder/navbar.html
airflow/www/templates/appbuilder/navbar_right.html
airflow_utils/__init__.py
airflow_utils/import_variable_connection.py
test_dataflow_airflow-2.10.10.dist-info/METADATA
test_dataflow_airflow-2.10.10.dist-info/WHEEL
test_dataflow_airflow-2.10.10.dist-info/top_level.txt
test_dataflow_airflow-2.10.10.dist-info/RECORD
