Metadata-Version: 2.4
Name: test-dataflow-airflow
Version: 2.10.10
Summary: Airflow customized for Dataflow
Home-page: https://github.com/Digital-Back-Office/dataflow-airflow
Author: Dataflow
Requires-Dist: apache-airflow==2.10.5
Requires-Dist: apache-airflow-providers-postgres
Requires-Dist: apache-airflow-providers-amazon
Requires-Dist: apache-airflow-providers-cncf-kubernetes
Requires-Dist: eval_type_backport
Dynamic: author
Dynamic: home-page
Dynamic: requires-dist
Dynamic: summary
